CHANGELOG
LICENSE
MANIFEST.in
README.rst
buildout.cfg
setup.cfg
setup.py
tangled.auth.egg-info/PKG-INFO
tangled.auth.egg-info/SOURCES.txt
tangled.auth.egg-info/dependency_links.txt
tangled.auth.egg-info/entry_points.txt
tangled.auth.egg-info/requires.txt
tangled.auth.egg-info/top_level.txt
tangled/auth/__init__.py
tangled/auth/abcs.py
tangled/auth/authentication.py
tangled/auth/authorization.py
tangled/auth/command.py
tangled/auth/tests/__init__.py
tangled/auth/tests/tests.py